Secondlock/__init__.py
cli42ndLock-0.0.3.data/scripts/cli42ndlock
cli42ndLock-0.0.3.dist-info/LICENSE
cli42ndLock-0.0.3.dist-info/METADATA
cli42ndLock-0.0.3.dist-info/WHEEL
cli42ndLock-0.0.3.dist-info/top_level.txt
cli42ndLock-0.0.3.dist-info/RECORD
