Metadata-Version: 2.1
Name: cli42ndLock
Version: 0.0.3
Summary: Client library and command line interface for 2ndLock
Home-page: https://github.com/symlinkgmbh/client-python/
Author: Ansgar Schmidt
Author-email: ansgar@symlink.de
Maintainer: Symlink GmbH
Maintainer-email: info@symlink.de
License: UNKNOWN
Platform: UNKNOWN
Classifier: Programming Language :: Python :: 3
Classifier: Development Status :: 4 - Beta
Classifier: License :: OSI Approved :: Apache Software License
Classifier: Environment :: Console
Classifier: Natural Language :: English
Classifier: Topic :: Communications
Requires-Python: >=3.0
Requires-Dist: click
Requires-Dist: pysha3
Requires-Dist: requests
Requires-Dist: dnspython
Requires-Dist: pycryptodome
Requires-Dist: python-dateutil
